Workbook
Name ProductIDs: 'Dim_Product'!$A$2:$A$61
Name CustomerIDs: 'Dim_Customer'!$A$2:$A$121
Name ChannelIDs: 'Dim_Channel'!$A$2:$A$5
Name PromotionIDs: 'Dim_Promotion'!$A$2:$A$11
Name SizesList: "XS,S,M,L,XL,XXL"

Sheet README
A1: Old Fashion – Data-Driven Fashion Brand
A2: Workbook purpose | B2: Synthetic but internally validated fashion dataset for Power BI / Excel modeling.
A3: Fact row count | B3: Fact_Sales contains exactly 1,500 order-line rows.
A4: Star schema | B4: Fact_Sales, Fact_Inventory_Monthly linked to dimensions using surrogate keys.
A5: Primary joins | B5: Fact_Sales[Date_Key]→Dim_Date[Date_Key]; Fact_Sales[Product_ID]→Dim_Product[Product_ID]; Fact_Sales[Customer_ID]→Dim_Customer[Customer_ID]; Fact_Sales[Channel_ID]→Dim_Channel[Channel_ID]; Fact_Sales[Promotion_ID]→Dim_Promotion[Promotion_ID].
A6: Validation | B6: Foreign keys in fact tables are constrained with data validation lists where practical, and every key value exists in its matching dimension table.
A7: Derived columns | B7: Fact_Sales revenue / cost / profit fields use formulas so the file is ready for audit and extension.
A8: Suggested Power BI model | B8: Use one-to-many relationships from each dimension to the fact tables.

Sheet Dim_Date
A1: Date_Key | B1: Date | C1: Day | D1: Month | E1: Month_Name | F1: Quarter | G1: Year | H1: Week_Number | I1: Day_of_Week | J1: Weekend_Flag | K1: Holiday_Flag | L1: Season
A2: 20250101 | B2: 45658 | C2: 1 | D2: 1 | E2: January | F2: Q1 | G2: 2025 | H2: 0 | I2: Wednesday | J2: No | K2: No | L2: Winter
A3: 20250102 | B3: 45659 | C3: 2 | D3: 1 | E3: January | F3: Q1 | G3: 2025 | H3: 0 | I3: Thursday | J3: No | K3: No | L3: Winter
A4: 20250103 | B4: 45660 | C4: 3 | D4: 1 | E4: January | F4: Q1 | G4: 2025 | H4: 0 | I4: Friday | J4: Yes | K4: No | L4: Winter
A5: 20250104 | B5: 45661 | C5: 4 | D5: 1 | E5: January | F5: Q1 | G5: 2025 | H5: 0 | I5: Saturday | J5: Yes | K5: No | L5: Winter
A6: 20250105 | B6: 45662 | C6: 5 | D6: 1 | E6: January | F6: Q1 | G6: 2025 | H6: 1 | I6: Sunday | J6: Yes | K6: No | L6: Winter
A7: 20250106 | B7: 45663 | C7: 6 | D7: 1 | E7: January | F7: Q1 | G7: 2025 | H7: 1 | I7: Monday | J7: No | K7: No | L7: Winter
A8: 20250107 | B8: 45664 | C8: 7 | D8: 1 | E8: January | F8: Q1 | G8: 2025 | H8: 1 | I8: Tuesday | J8: No | K8: No | L8: Winter
A9: 20250108 | B9: 45665 | C9: 8 | D9: 1 | E9: January | F9: Q1 | G9: 2025 | H9: 1 | I9: Wednesday | J9: No | K9: No | L9: Winter
A10: 20250109 | B10: 45666 | C10: 9 | D10: 1 | E10: January | F10: Q1 | G10: 2025 | H10: 1 | I10: Thursday | J10: No | K10: No | L10: Winter
A11: 20250110 | B11: 45667 | C11: 10 | D11: 1 | E11: January | F11: Q1 | G11: 2025 | H11: 1 | I11: Friday | J11: Yes | K11: No | L11: Winter
A12: 20250111 | B12: 45668 | C12: 11 | D12: 1 | E12: January | F12: Q1 | G12: 2025 | H12: 1 | I12: Saturday | J12: Yes | K12: No | L12: Winter
A13: 20250112 | B13: 45669 | C13: 12 | D13: 1 | E13: January | F13: Q1 | G13: 2025 | H13: 2 | I13: Sunday | J13: Yes | K13: No | L13: Winter
... A366: 20251231 | B366: 46022 | C366: 31 | D366: 12 | E366: December | F366: Q4 | G366: 2025 | H366: 52 | I366: Wednesday | J366: No | K366: No | L366: Winter

Sheet Dim_Product
A1: Product_ID | B1: SKU | C1: Product_Name | D1: Category | E1: Subcategory | F1: Gender | G1: Fabric_Type | H1: Color | I1: Core_Size_Run | J1: Base_List_Price | K1: Base_Unit_Cost | L1: Launch_Date | M1: Collection_Name | N1: Season | O1: Style_Theme | P1: Timelessness_Score | Q1: Trend_Score | R1: Supplier_ID | S1: Reorder_Level | T1: Lead_Time_Days | U1: Status
A2: P001 | B2: OF-SH-1BE | C2: Beige Oxford Shirt | D2: Shirts | E2: Oxford Shirt | F2: Unisex | G2: Cotton | H2: Beige | I2: S/M/L/XL | J2: 40 | K2: 17 | L2: 45910 | M2: Heritage 2025 | N2: All Season | O2: Vintage | P2: 3 | Q2: 1 | R2: S06 | S2: 18 | T2: 35 | U2: Active
A3: P002 | B3: OF-SH-1NA | C3: Navy Oxford Shirt | D3: Shirts | E3: Oxford Shirt | F3: Unisex | G3: Cotton | H3: Navy | I3: S/M/L/XL | J3: 40 | K3: 17 | L3: 45662 | M3: Heritage 2025 | N3: All Season | O3: Casual Old Fashion | P3: 5 | Q3: 1 | R3: S05 | S3: 24 | T3: 35 | U3: Active
A4: P003 | B4: OF-SH-1WH | C4: White Oxford Shirt | D4: Shirts | E4: Oxford Shirt | F4: Unisex | G4: Cotton | H4: White | I4: S/M/L/XL | J4: 42 | K4: 20 | L4: 45879 | M4: Heritage 2025 | N4: All Season | O4: Vintage | P4: 5 | Q4: 4 | R4: S03 | S4: 30 | T4: 21 | U4: Active
A5: P004 | B5: OF-SH-1OL | C5: Olive Oxford Shirt | D5: Shirts | E5: Oxford Shirt | F5: Unisex | G5: Cotton | H5: Olive | I5: S/M/L/XL | J5: 42 | K5: 19 | L5: 45658 | M5: Foundations 2025 | N5: All Season | O5: Classic | P5: 4 | Q5: 3 | R5: S05 | S5: 30 | T5: 14 | U5: Active
A6: P005 | B6: OF-SH-2BE | C6: Beige Linen Shirt | D6: Shirts | E6: Linen Shirt | F6: Unisex | G6: Linen | H6: Beige | I6: S/M/L/XL | J6: 52 | K6: 20 | L6: 45809 | M6: Atelier 2025 | N6: Spring/Summer | O6: Minimal | P6: 5 | Q6: 3 | R6: S05 | S6: 24 | T6: 14 | U6: Active
A7: P006 | B7: OF-SH-2NA | C7: Navy Linen Shirt | D7: Shirts | E7: Linen Shirt | F7: Unisex | G7: Linen | H7: Navy | I7: S/M/L/XL | J7: 46 | K7: 21 | L7: 45717 | M7: Heritage 2025 | N7: Spring/Summer | O7: Classic | P7: 4 | Q7: 3 | R7: S04 | S7: 30 | T7: 21 | U7: Active
A8: P007 | B8: OF-SH-2WH | C8: White Linen Shirt | D8: Shirts | E8: Linen Shirt | F8: Unisex | G8: Linen | H8: White | I8: S/M/L/XL | J8: 50 | K8: 22 | L8: 45698 | M8: Atelier 2025 | N8: Spring/Summer | O8: Classic | P8: 5 | Q8: 2 | R8: S05 | S8: 24 | T8: 21 | U8: Active
A9: P008 | B9: OF-SH-2OL | C9: Olive Linen Shirt | D9: Shirts | E9: Linen Shirt | F9: Unisex | G9: Linen | H9: Olive | I9: S/M/L/XL | J9: 52 | K9: 23 | L9: 45736 | M9: Heritage 2025 | N9: Spring/Summer | O9: Minimal | P9: 3 | Q9: 2 | R9: S01 | S9: 30 | T9: 35 | U9: Active
A10: P009 | B10: OF-SH-3BE | C10: Beige Striped Shirt | D10: Shirts | E10: Striped Shirt | F10: Unisex | G10: Cotton | H10: Beige | I10: S/M/L/XL | J10: 48 | K10: 19 | L10: 45708 | M10: Atelier 2025 | N10: All Season | O10: Minimal | P10: 3 | Q10: 4 | R10: S04 | S10: 36 | T10: 21 | U10: Active
A11: P010 | B11: OF-SH-3NA | C11: Navy Striped Shirt | D11: Shirts | E11: Striped Shirt | F11: Unisex | G11: Cotton | H11: Navy | I11: S/M/L/XL | J11: 48 | K11: 20 | L11: 45708 | M11: Atelier 2025 | N11: All Season | O11: Minimal | P11: 5 | Q11: 4 | R11: S05 | S11: 36 | T11: 28 | U11: Active
A12: P011 | B12: OF-SH-3WH | C12: White Striped Shirt | D12: Shirts | E12: Striped Shirt | F12: Unisex | G12: Cotton | H12: White | I12: S/M/L/XL | J12: 46 | K12: 20 | L12: 45884 | M12: Heritage 2025 | N12: All Season | O12: Classic | P12: 3 | Q12: 2 | R12: S06 | S12: 24 | T12: 35 | U12: Active
A13: P012 | B13: OF-SH-3OL | C13: Olive Striped Shirt | D13: Shirts | E13: Striped Shirt | F13: Unisex | G13: Cotton | H13: Olive | I13: S/M/L/XL | J13: 44 | K13: 22 | L13: 45828 | M13: Foundations 2025 | N13: All Season | O13: Casual Old Fashion | P13: 4 | Q13: 1 | R13: S06 | S13: 18 | T13: 28 | U13: Active
... A61: P060 | B61: OF-KN-3OL | C61: Olive Turtleneck | D61: Knitwear | E61: Turtleneck | F61: Unisex | G61: Merino Wool | H61: Olive | I61: S/M/L/XL | J61: 72 | K61: 36 | L61: 45672 | M61: Foundations 2025 | N61: Fall/Winter | O61: Classic | P61: 4 | Q61: 3 | R61: S06 | S61: 36 | T61: 21 | U61: Active

Sheet Dim_Customer
A1: Customer_ID | B1: Gender | C1: Age | D1: City | E1: Country | F1: Customer_Segment | G1: Registration_Date | H1: Preferred_Channel_ID | I1: Loyalty_Status
A2: C001 | B2: Men | C2: 31 | D2: Kuwait City | E2: Jordan | F2: Premium Tailoring | G2: 45432 | H2: CH04 | I2: Bronze
A3: C002 | B3: Men | C3: 40 | D3: Amman | E3: UAE | F3: Digital Native | G3: 45331 | H3: CH03 | I3: Silver
A4: C003 | B4: Men | C4: 41 | D4: Mansoura | E4: Saudi Arabia | F4: Classic Loyalist | G4: 45367 | H4: CH04 | I4: Silver
A5: C004 | B5: Men | C5: 37 | D5: Cairo | E5: Kuwait | F5: Digital Native | G5: 45430 | H5: CH03 | I5: Gold
A6: C005 | B6: Women | C6: 35 | D6: Amman | E6: Qatar | F6: Premium Tailoring | G6: 45405 | H6: CH02 | I6: Silver
A7: C006 | B7: Men | C7: 21 | D7: Dubai | E7: Qatar | F7: Classic Loyalist | G7: 45634 | H7: CH01 | I7: Silver
A8: C007 | B8: Men | C8: 55 | D8: Riyadh | E8: Saudi Arabia | F8: Occasional Buyer | G8: 45644 | H8: CH01 | I8: Silver
A9: C008 | B9: Men | C9: 39 | D9: Alexandria | E9: Qatar | F9: Value Seeker | G9: 45393 | H9: CH01 | I9: Bronze
A10: C009 | B10: Women | C10: 32 | D10: Kuwait City | E10: Kuwait | F10: Classic Loyalist | G10: 45645 | H10: CH02 | I10: Bronze
A11: C010 | B11: Women | C11: 32 | D11: Kuwait City | E11: UAE | F11: Value Seeker | G11: 45413 | H11: CH01 | I11: Bronze
A12: C011 | B12: Women | C12: 55 | D12: Amman | E12: Egypt | F12: Value Seeker | G12: 45624 | H12: CH04 | I12: Gold
A13: C012 | B13: Men | C13: 50 | D13: Amman | E13: Egypt | F13: Value Seeker | G13: 45300 | H13: CH01 | I13: Silver
... A121: C120 | B121: Men | C121: 53 | D121: Jeddah | E121: Kuwait | F121: Value Seeker | G121: 45476 | H121: CH01 | I121: Gold

Sheet Dim_Channel
A1: Channel_ID | B1: Channel_Name
A2: CH01 | B2: Online
A3: CH02 | B3: Store
A4: CH03 | B4: Instagram
A5: CH04 | B5: Marketplace

Sheet Dim_Promotion
A1: Promotion_ID | B1: Promotion_Name | C1: Discount_Type | D1: Discount_Value | E1: Target_Category | F1: Start_Date | G1: End_Date
A2: PR00 | B2: No Promotion | C2: None | D2: 0 | E2: All
A3: PR01 | B3: Winter Launch 10% | C3: Percent | D3: 0.1 | E3: Outerwear | F3: 45658 | G3: 45703
A4: PR02 | B4: Valentine Styling 15% | C4: Percent | D4: 0.15 | E4: Dresses | F4: 45689 | G4: 45708
A5: PR03 | B5: Spring Classics 8% | C5: Percent | D5: 0.08 | E5: Shirts | F5: 45717 | G5: 45762
A6: PR04 | B6: Summer Linen 12% | C6: Percent | D6: 0.12 | E6: Shirts | F6: 45809 | G6: 45853
A7: PR05 | B7: Midyear Sale 20% | C7: Percent | D7: 0.2 | E7: All | F7: 45828 | G7: 45843
A8: PR06 | B8: Heritage Week 10% | C8: Percent | D8: 0.1 | E8: Trousers | F8: 45879 | G8: 45889
A9: PR07 | B9: Fall Tailoring 12% | C9: Percent | D9: 0.12 | E9: Blazers | F9: 45901 | G9: 45945
A10: PR08 | B10: Black Friday 25% | C10: Percent | D10: 0.25 | E10: All | F10: 45985 | G10: 45991
A11: PR09 | B11: Holiday Gifting 15% | C11: Percent | D11: 0.15 | E11: Knitwear | F11: 45992 | G11: 46015

Sheet Fact_Sales
A1: Sales_Line_ID | B1: Order_ID | C1: Date_Key | D1: Customer_ID | E1: Product_ID | F1: Size | G1: Channel_ID | H1: Promotion_ID | I1: List_Price | J1: Discount_Pct | K1: Net_Unit_Price | L1: Quantity_Sold | M1: Gross_Revenue | N1: Unit_Cost | O1: Total_Cost | P1: Gross_Profit | Q1: Returned_Flag | R1: Returned_Quantity | S1: Net_Revenue | T1: Product_Name_Lookup | U1: Category_Lookup | V1: Customer_Segment_Lookup | W1: Channel_Name_Lookup | X1: Promotion_Name_Lookup
A2: SL0001 | B2: O010001 | C2: 20250310 | D2: C042 | E2: P006 | F2: M | G2: CH02 | H2: PR03 | I2: 46 | J2: 0.08 | K2: =I2*(1-J2) | L2: 1 | M2: =K2*L2 | N2: 21.02 | O2: =N2*L2 | P2: =M2-O2 | Q2: No | R2: 0 | S2: =M2-(R2*K2) | T2: =VLOOKUP(E2,Dim_Product!$A$2:$Q$61,3,FALSE) | U2: =VLOOKUP(E2,Dim_Product!$A$2:$Q$61,4,FALSE) | V2: =VLOOKUP(D2,Dim_Customer!$A$2:$I$121,6,FALSE) | W2: =VLOOKUP(G2,Dim_Channel!$A$2:$B$5,2,FALSE) | X2: =VLOOKUP(H2,Dim_Promotion!$A$2:$G$11,2,FALSE)
A3: SL0002 | B3: O010001 | C3: 20251112 | D3: C079 | E3: P060 | F3: XL | G3: CH04 | H3: PR00 | I3: 72 | J3: 0 | K3: =I3*(1-J3) | L3: 1 | M3: =K3*L3 | N3: 36.9 | O3: =N3*L3 | P3: =M3-O3 | Q3: No | R3: 0 | S3: =M3-(R3*K3) | T3: =VLOOKUP(E3,Dim_Product!$A$2:$Q$61,3,FALSE) | U3: =VLOOKUP(E3,Dim_Product!$A$2:$Q$61,4,FALSE) | V3: =VLOOKUP(D3,Dim_Customer!$A$2:$I$121,6,FALSE) | W3: =VLOOKUP(G3,Dim_Channel!$A$2:$B$5,2,FALSE) | X3: =VLOOKUP(H3,Dim_Promotion!$A$2:$G$11,2,FALSE)
A4: SL0003 | B4: O010002 | C4: 20250128 | D4: C078 | E4: P040 | F4: XS | G4: CH01 | H4: PR00 | I4: 72 | J4: 0 | K4: =I4*(1-J4) | L4: 1 | M4: =K4*L4 | N4: 33.63 | O4: =N4*L4 | P4: =M4-O4 | Q4: No | R4: 0 | S4: =M4-(R4*K4) | T4: =VLOOKUP(E4,Dim_Product!$A$2:$Q$61,3,FALSE) | U4: =VLOOKUP(E4,Dim_Product!$A$2:$Q$61,4,FALSE) | V4: =VLOOKUP(D4,Dim_Customer!$A$2:$I$121,6,FALSE) | W4: =VLOOKUP(G4,Dim_Channel!$A$2:$B$5,2,FALSE) | X4: =VLOOKUP(H4,Dim_Promotion!$A$2:$G$11,2,FALSE)
A5: SL0004 | B5: O010002 | C5: 20250615 | D5: C098 | E5: P005 | F5: M | G5: CH01 | H5: PR00 | I5: 50 | J5: 0 | K5: =I5*(1-J5) | L5: 2 | M5: =K5*L5 | N5: 20.2 | O5: =N5*L5 | P5: =M5-O5 | Q5: No | R5: 0 | S5: =M5-(R5*K5) | T5: =VLOOKUP(E5,Dim_Product!$A$2:$Q$61,3,FALSE) | U5: =VLOOKUP(E5,Dim_Product!$A$2:$Q$61,4,FALSE) | V5: =VLOOKUP(D5,Dim_Customer!$A$2:$I$121,6,FALSE) | W5: =VLOOKUP(G5,Dim_Channel!$A$2:$B$5,2,FALSE) | X5: =VLOOKUP(H5,Dim_Promotion!$A$2:$G$11,2,FALSE)
A6: SL0005 | B6: O010003 | C6: 20250809 | D6: C100 | E6: P014 | F6: XL | G6: CH02 | H6: PR00 | I6: 61 | J6: 0 | K6: =I6*(1-J6) | L6: 1 | M6: =K6*L6 | N6: 26.68 | O6: =N6*L6 | P6: =M6-O6 | Q6: No | R6: 0 | S6: =M6-(R6*K6) | T6: =VLOOKUP(E6,Dim_Product!$A$2:$Q$61,3,FALSE) | U6: =VLOOKUP(E6,Dim_Product!$A$2:$Q$61,4,FALSE) | V6: =VLOOKUP(D6,Dim_Customer!$A$2:$I$121,6,FALSE) | W6: =VLOOKUP(G6,Dim_Channel!$A$2:$B$5,2,FALSE) | X6: =VLOOKUP(H6,Dim_Promotion!$A$2:$G$11,2,FALSE)
A7: SL0006 | B7: O010003 | C7: 20250323 | D7: C057 | E7: P039 | F7: M | G7: CH02 | H7: PR00 | I7: 74 | J7: 0 | K7: =I7*(1-J7) | L7: 1 | M7: =K7*L7 | N7: 37.28 | O7: =N7*L7 | P7: =M7-O7 | Q7: No | R7: 0 | S7: =M7-(R7*K7) | T7: =VLOOKUP(E7,Dim_Product!$A$2:$Q$61,3,FALSE) | U7: =VLOOKUP(E7,Dim_Product!$A$2:$Q$61,4,FALSE) | V7: =VLOOKUP(D7,Dim_Customer!$A$2:$I$121,6,FALSE) | W7: =VLOOKUP(G7,Dim_Channel!$A$2:$B$5,2,FALSE) | X7: =VLOOKUP(H7,Dim_Promotion!$A$2:$G$11,2,FALSE)
A8: SL0007 | B8: O010004 | C8: 20251117 | D8: C029 | E8: P007 | F8: S | G8: CH03 | H8: PR00 | I8: 52 | J8: 0 | K8: =I8*(1-J8) | L8: 1 | M8: =K8*L8 | N8: 22.18 | O8: =N8*L8 | P8: =M8-O8 | Q8: No | R8: 0 | S8: =M8-(R8*K8) | T8: =VLOOKUP(E8,Dim_Product!$A$2:$Q$61,3,FALSE) | U8: =VLOOKUP(E8,Dim_Product!$A$2:$Q$61,4,FALSE) | V8: =VLOOKUP(D8,Dim_Customer!$A$2:$I$121,6,FALSE) | W8: =VLOOKUP(G8,Dim_Channel!$A$2:$B$5,2,FALSE) | X8: =VLOOKUP(H8,Dim_Promotion!$A$2:$G$11,2,FALSE)
A9: SL0008 | B9: O010004 | C9: 20250329 | D9: C012 | E9: P004 | F9: L | G9: CH01 | H9: PR00 | I9: 44 | J9: 0 | K9: =I9*(1-J9) | L9: 1 | M9: =K9*L9 | N9: 19.73 | O9: =N9*L9 | P9: =M9-O9 | Q9: No | R9: 0 | S9: =M9-(R9*K9) | T9: =VLOOKUP(E9,Dim_Product!$A$2:$Q$61,3,FALSE) | U9: =VLOOKUP(E9,Dim_Product!$A$2:$Q$61,4,FALSE) | V9: =VLOOKUP(D9,Dim_Customer!$A$2:$I$121,6,FALSE) | W9: =VLOOKUP(G9,Dim_Channel!$A$2:$B$5,2,FALSE) | X9: =VLOOKUP(H9,Dim_Promotion!$A$2:$G$11,2,FALSE)
A10: SL0009 | B10: O010005 | C10: 20250622 | D10: C067 | E10: P046 | F10: S | G10: CH04 | H10: PR00 | I10: 64 | J10: 0 | K10: =I10*(1-J10) | L10: 2 | M10: =K10*L10 | N10: 33.37 | O10: =N10*L10 | P10: =M10-O10 | Q10: No | R10: 0 | S10: =M10-(R10*K10) | T10: =VLOOKUP(E10,Dim_Product!$A$2:$Q$61,3,FALSE) | U10: =VLOOKUP(E10,Dim_Product!$A$2:$Q$61,4,FALSE) | V10: =VLOOKUP(D10,Dim_Customer!$A$2:$I$121,6,FALSE) | W10: =VLOOKUP(G10,Dim_Channel!$A$2:$B$5,2,FALSE) | X10: =VLOOKUP(H10,Dim_Promotion!$A$2:$G$11,2,FALSE)
A11: SL0010 | B11: O010005 | C11: 20250330 | D11: C091 | E11: P030 | F11: XS | G11: CH02 | H11: PR00 | I11: 108 | J11: 0 | K11: =I11*(1-J11) | L11: 1 | M11: =K11*L11 | N11: 55.9 | O11: =N11*L11 | P11: =M11-O11 | Q11: No | R11: 0 | S11: =M11-(R11*K11) | T11: =VLOOKUP(E11,Dim_Product!$A$2:$Q$61,3,FALSE) | U11: =VLOOKUP(E11,Dim_Product!$A$2:$Q$61,4,FALSE) | V11: =VLOOKUP(D11,Dim_Customer!$A$2:$I$121,6,FALSE) | W11: =VLOOKUP(G11,Dim_Channel!$A$2:$B$5,2,FALSE) | X11: =VLOOKUP(H11,Dim_Promotion!$A$2:$G$11,2,FALSE)
A12: SL0011 | B12: O010006 | C12: 20250706 | D12: C076 | E12: P057 | F12: L | G12: CH03 | H12: PR00 | I12: 76 | J12: 0 | K12: =I12*(1-J12) | L12: 1 | M12: =K12*L12 | N12: 36.11 | O12: =N12*L12 | P12: =M12-O12 | Q12: No | R12: 0 | S12: =M12-(R12*K12) | T12: =VLOOKUP(E12,Dim_Product!$A$2:$Q$61,3,FALSE) | U12: =VLOOKUP(E12,Dim_Product!$A$2:$Q$61,4,FALSE) | V12: =VLOOKUP(D12,Dim_Customer!$A$2:$I$121,6,FALSE) | W12: =VLOOKUP(G12,Dim_Channel!$A$2:$B$5,2,FALSE) | X12: =VLOOKUP(H12,Dim_Promotion!$A$2:$G$11,2,FALSE)
A13: SL0012 | B13: O010006 | C13: 20251225 | D13: C074 | E13: P015 | F13: L | G13: CH02 | H13: PR00 | I13: 58 | J13: 0 | K13: =I13*(1-J13) | L13: 1 | M13: =K13*L13 | N13: 26.97 | O13: =N13*L13 | P13: =M13-O13 | Q13: No | R13: 0 | S13: =M13-(R13*K13) | T13: =VLOOKUP(E13,Dim_Product!$A$2:$Q$61,3,FALSE) | U13: =VLOOKUP(E13,Dim_Product!$A$2:$Q$61,4,FALSE) | V13: =VLOOKUP(D13,Dim_Customer!$A$2:$I$121,6,FALSE) | W13: =VLOOKUP(G13,Dim_Channel!$A$2:$B$5,2,FALSE) | X13: =VLOOKUP(H13,Dim_Promotion!$A$2:$G$11,2,FALSE)
... A1501: SL1500 | B1501: O010750 | C1501: 20250914 | D1501: C006 | E1501: P046 | F1501: M | G1501: CH01 | H1501: PR00 | I1501: 66 | J1501: 0 | K1501: =I1501*(1-J1501) | L1501: 1 | M1501: =K1501*L1501 | N1501: 33.56 | O1501: =N1501*L1501 | P1501: =M1501-O1501 | Q1501: No | R1501: 0 | S1501: =M1501-(R1501*K1501) | T1501: =VLOOKUP(E1501,Dim_Product!$A$2:$Q$61,3,FALSE) | U1501: =VLOOKUP(E1501,Dim_Product!$A$2:$Q$61,4,FALSE) | V1501: =VLOOKUP(D1501,Dim_Customer!$A$2:$I$121,6,FALSE) | W1501: =VLOOKUP(G1501,Dim_Channel!$A$2:$B$5,2,FALSE) | X1501: =VLOOKUP(H1501,Dim_Promotion!$A$2:$G$11,2,FALSE)

Sheet Fact_Inventory_Monthly
A1: Month_Key | B1: Product_ID | C1: Opening_Stock | D1: Received_Stock | E1: Sold_Stock | F1: Returned_Stock | G1: Damaged_Stock | H1: Closing_Stock | I1: Reorder_Level | J1: Stockout_Flag | K1: Overstock_Flag | L1: Warehouse_Location
A2: 20250101 | B2: P001 | C2: 53 | D2: 16 | E2: 0 | F2: 0 | G2: 1 | H2: 68 | I2: 18 | J2: No | K2: Yes | L2: North WH
A3: 20250201 | B3: P001 | C3: 68 | D3: 0 | E3: 1 | F3: 0 | G3: 1 | H3: 66 | I3: 18 | J3: No | K3: Yes | L3: North WH
A4: 20250301 | B4: P001 | C4: 66 | D4: 8 | E4: 1 | F4: 0 | G4: 2 | H4: 71 | I4: 18 | J4: No | K4: Yes | L4: North WH
A5: 20250401 | B5: P001 | C5: 71 | D5: 6 | E5: 5 | F5: 0 | G5: 1 | H5: 71 | I5: 18 | J5: No | K5: Yes | L5: North WH
A6: 20250501 | B6: P001 | C6: 71 | D6: 8 | E6: 6 | F6: 0 | G6: 0 | H6: 73 | I6: 18 | J6: No | K6: Yes | L6: Main WH
A7: 20250601 | B7: P001 | C7: 73 | D7: 0 | E7: 0 | F7: 0 | G7: 0 | H7: 73 | I7: 18 | J7: No | K7: Yes | L7: Main WH
A8: 20250701 | B8: P001 | C8: 73 | D8: 0 | E8: 3 | F8: 0 | G8: 1 | H8: 69 | I8: 18 | J8: No | K8: Yes | L8: North WH
A9: 20250801 | B9: P001 | C9: 69 | D9: 0 | E9: 1 | F9: 0 | G9: 0 | H9: 68 | I9: 18 | J9: No | K9: Yes | L9: Main WH
A10: 20250901 | B10: P001 | C10: 68 | D10: 3 | E10: 3 | F10: 0 | G10: 0 | H10: 68 | I10: 18 | J10: No | K10: Yes | L10: Main WH
A11: 20251001 | B11: P001 | C11: 68 | D11: 0 | E11: 0 | F11: 0 | G11: 0 | H11: 68 | I11: 18 | J11: No | K11: Yes | L11: North WH
A12: 20251101 | B12: P001 | C12: 68 | D12: 0 | E12: 2 | F12: 0 | G12: 2 | H12: 64 | I12: 18 | J12: No | K12: Yes | L12: Main WH
A13: 20251201 | B13: P001 | C13: 64 | D13: 1 | E13: 4 | F13: 0 | G13: 0 | H13: 61 | I13: 18 | J13: No | K13: Yes | L13: North WH
... A721: 20251201 | B721: P060 | C721: 82 | D721: 2 | E721: 7 | F721: 0 | G721: 1 | H721: 76 | I721: 36 | J721: No | K721: No | L721: Main WH

Sheet KPI_Summary
A1: Metric | B1: Value
A2: Total Orders | B2: 750
A3: Total Units Sold | B3: =SUM(Fact_Sales!L2:L1501)
A4: Gross Revenue | B4: =SUM(Fact_Sales!M2:M1501)
A5: Net Revenue | B5: =SUM(Fact_Sales!S2:S1501)
A6: Total Cost | B6: =SUM(Fact_Sales!O2:O1501)
A7: Gross Profit | B7: =SUM(Fact_Sales!P2:P1501)
A8: Return Units | B8: =SUM(Fact_Sales!R2:R1501)
A9: Return Rate | B9: =IF(B3=0,0,B8/B3)
A10: Avg Discount | B10: =AVERAGE(Fact_Sales!J2:J1501)
